pythonRSCdev/__init__.py
pythonRSCdev/assembler.py
pythonRSCdev/classes.py
pythonRSCdev/cli.py
pythonRSCdev/emulator.py
pythonRSC_dev-1.1.3.dist-info/LICENSE
pythonRSC_dev-1.1.3.dist-info/METADATA
pythonRSC_dev-1.1.3.dist-info/WHEEL
pythonRSC_dev-1.1.3.dist-info/entry_points.txt
pythonRSC_dev-1.1.3.dist-info/top_level.txt
pythonRSC_dev-1.1.3.dist-info/RECORD
