Metadata-Version: 2.1
Name: pythonRSC-dev
Version: 1.1.3
Summary: pythonRSC-dev is an emulator for the RSC architecture written in Python, but the development branch!
Author-email: Calastrophe <vmxoperation@proton.me>
Project-URL: Homepage, https://github.com/Calastrophe/pythonRSC-dev
Project-URL: Bug Tracker, https://github.com/Calastrophe/pythonRSC-dev/issues
Classifier: Programming Language :: Python :: 3.10
Classifier: License :: OSI Approved :: GNU General Public License v3 (GPLv3)
Classifier: Operating System :: OS Independent
Requires-Python: >=3.10
License-File: LICENSE
Requires-Dist: numpy
Requires-Dist: pythonCFG
